<Properties StartupConfiguration="{03825FD9-5599-E1EB-7774-D098487434F0}|">
  <MonoDevelop.Ide.Workbench ActiveDocument="Assets/Player.cs">
    <Files>
      <File FileName="Assets/Player.cs" Line="37" Column="1" />
    </Files>
    <Pads>
      <Pad Id="ProjectPad">
        <State name="__root__">
          <Node name="4_Argon_Assault" expanded="True">
            <Node name="Assets" expanded="True">
              <Node name="Player.cs" selected="True" />
            </Node>
          </Node>
        </State>
      </Pad>
    </Pads>
  </MonoDevelop.Ide.Workbench>
  <MonoDevelop.Ide.DebuggingService.PinnedWatches />
  <MonoDevelop.Ide.Workspace ActiveConfiguration="Debug" />
  <MonoDevelop.Ide.ItemProperties.Assembly-CSharp PreferredExecutionTarget="ef5a61ba-9ca9-43ea-a47f-8029fed8401b" />
  <MonoDevelop.Ide.DebuggingService.Breakpoints>
    <BreakpointStore />
  </MonoDevelop.Ide.DebuggingService.Breakpoints>
  <MultiItemStartupConfigurations />
</Properties>